sentence_spliter/__init__.py
sentence_spliter/architect/__init__.py
sentence_spliter/architect/graph_component.py
sentence_spliter/architect/sequence.py
sentence_spliter/cutter4grammar/__init__.py
sentence_spliter/cutter4grammar/condition.py
sentence_spliter/cutter4grammar/en_sequence.py
sentence_spliter/cutter4grammar/logic.py
sentence_spliter/cutter4grammar/long_handler.py
sentence_spliter/cutter4grammar/operation.py
sentence_spliter/cutter4grammar/symbol.py
sentence_spliter/cutter4grammar/weights_list.txt
sentence_spliter/cutter4grammar/white_list.txt
sentence_spliter/en_cutter/__init__.py
sentence_spliter/en_cutter/condition.py
sentence_spliter/en_cutter/en_sequence.py
sentence_spliter/en_cutter/logic.py
sentence_spliter/en_cutter/long_handler.py
sentence_spliter/en_cutter/operation.py
sentence_spliter/en_cutter/symbol.py
sentence_spliter/en_cutter/weights_list.txt
sentence_spliter/en_cutter/white_list.txt
sentence_spliter/utility/__init__.py
sentence_spliter/utility/arrary.py
sentence_spliter/utility/file_opt.py
sentence_spliter/utility/trie.py
sentence_spliter/zh_cutter/__init__.py
sentence_spliter/zh_cutter/condition.py
sentence_spliter/zh_cutter/logic.py
sentence_spliter/zh_cutter/long_handler.py
sentence_spliter/zh_cutter/operation.py
sentence_spliter/zh_cutter/symbol.py
sentence_spliter/zh_cutter/weights_list.txt
sentence_spliter/zh_cutter/white_list.txt
sentence_spliter/zh_cutter/zh_sequence.py
sentence_spliter-2.1.8.dist-info/LICENSE
sentence_spliter-2.1.8.dist-info/METADATA
sentence_spliter-2.1.8.dist-info/WHEEL
sentence_spliter-2.1.8.dist-info/top_level.txt
sentence_spliter-2.1.8.dist-info/RECORD
