Metadata-Version: 2.1
Name: sentence-spliter
Version: 2.1.8
Summary: This is a sentence cutting tool, currently support English & Chinese
Author: jianwei zhao
Author-email: zhaojianwei@163.com
License: MIT
Classifier: Programming Language :: Python :: 3.6
Classifier: Programming Language :: Python :: 3.7
Classifier: Programming Language :: Python :: 3.8
Classifier: License :: OSI Approved :: MIT License
License-File: LICENSE
Requires-Dist: attrd (>=0.0.3)
Requires-Dist: attrdict (>=2.0.1)
Requires-Dist: attrs (>=19.3.0)
Requires-Dist: importlib-metadata (>=1.6.0)
Requires-Dist: loguru (>=0.5.3)
Requires-Dist: more-itertools (>=8.2.0)
Requires-Dist: packaging (>=20.3)
Requires-Dist: pluggy (>=0.13.1)
Requires-Dist: py (>=1.8.1)
Requires-Dist: pyparsing (>=2.4.7)
Requires-Dist: pytest (>=5.4.1)
Requires-Dist: six (>=1.14.0)
Requires-Dist: wcwidth (>=0.1.9)
Requires-Dist: zipp (>=3.1.0)
